gwpoffpm/__init__.py
gwpoffpm/dataset.py
gwpoffpm/evaluate.py
gwpoffpm/offset_predictor.py
gwpoffpm/sample.py
gwpoffpm/train.py
gwpoffpm-1.0.0.dist-info/LICENSE
gwpoffpm-1.0.0.dist-info/METADATA
gwpoffpm-1.0.0.dist-info/WHEEL
gwpoffpm-1.0.0.dist-info/top_level.txt
gwpoffpm-1.0.0.dist-info/RECORD
